beginai_cli/__init__.py
beginai_cli/main.py
beginai_cli-1.17.0.dist-info/METADATA
beginai_cli-1.17.0.dist-info/WHEEL
beginai_cli-1.17.0.dist-info/entry_points.txt
beginai_cli-1.17.0.dist-info/top_level.txt
beginai_cli-1.17.0.dist-info/RECORD
