Metadata-Version: 2.1
Name: beginai-cli
Version: 1.17.0
Summary: A CLI part of Begin AI ecosystesm that enables batch processing with minimum code.
Home-page: https://docs.begin.ai
Author: Begin AI Research & Engineering
Author-email: engineering@begin.ai
License: Proprietary
Platform: UNKNOWN
Classifier: Programming Language :: Python :: 3
Classifier: Operating System :: OS Independent
Requires-Python: >=3.6
Requires-Dist: requests
Requires-Dist: typer[all]
Requires-Dist: beginai
